ocr_loc/__init__.py
ocr_loc/corp.py
ocr_loc/text_local.py
ocr_loc-0.1.1.dist-info/METADATA
ocr_loc-0.1.1.dist-info/WHEEL
ocr_loc-0.1.1.dist-info/licenses/LICENSE
ocr_loc-0.1.1.dist-info/RECORD
