Metadata-Version: 2.4
Name: ocr-loc
Version: 0.1.1
Summary: Add your description here
Author-email: kin9-0rz <kin9-0rz@outlook.com>
License-File: LICENSE
Requires-Python: >=3.8
Requires-Dist: addict>=2.4.0
Requires-Dist: datasets>=3.3.2
Requires-Dist: modelscope>=1.23.1
Requires-Dist: numpy==1.26.4
Requires-Dist: opencv-python>=4.11.0.86
Requires-Dist: pillow>=11.1.0
Requires-Dist: pyclipper>=1.3.0.post6
Requires-Dist: pycocotools>=2.0.8
Requires-Dist: setuptools>=75.8.2
Requires-Dist: shapely>=2.0.7
Requires-Dist: simplejson>=3.20.1
Requires-Dist: sortedcontainers>=2.4.0
Requires-Dist: supervision==0.21.0
Requires-Dist: termcolor>=2.5.0
Requires-Dist: timm>=1.0.15
Requires-Dist: torch>=2.2.2
Requires-Dist: torchvision>=0.17.2
Requires-Dist: transformers>=4.49.0
Requires-Dist: yapf>=0.43.0
